minimux/__init__.py
minimux/__main__.py
minimux/attr.py
minimux/buffer.py
minimux/colour.py
minimux/config.py
minimux/padding.py
minimux/range.py
minimux/runner.py
minimux/utils.py
minimux-2.0.0.dist-info/METADATA
minimux-2.0.0.dist-info/WHEEL
minimux-2.0.0.dist-info/entry_points.txt
minimux-2.0.0.dist-info/licenses/LICENSE
minimux-2.0.0.dist-info/RECORD
