Metadata-Version: 2.4
Name: minimux
Version: 2.0.0
Summary: A lightweight non-interactive terminal multiplexer.
License-File: LICENSE
Author: Dominic Price
Author-email: dominicprice@outlook.com
Requires-Python: >=3.10,<4.0
Classifier: Programming Language :: Python :: 3
Classifier: Programming Language :: Python :: 3.10
Classifier: Programming Language :: Python :: 3.11
Classifier: Programming Language :: Python :: 3.12
Classifier: Programming Language :: Python :: 3.13
Classifier: Programming Language :: Python :: 3.14
Requires-Dist: click (>=8.1.8,<9.0.0)
Requires-Dist: pyte (>=0.8.2,<0.9.0)
